webmention/__init__.py
webmention/admin.py
webmention/checks.py
webmention/middleware.py
webmention/models.py
webmention/resolution.py
webmention/urls.py
webmention/views.py
webmention/migrations/0001_initial.py
webmention/migrations/__init__.py
django_webmention-3.0.0.dist-info/LICENSE
django_webmention-3.0.0.dist-info/METADATA
django_webmention-3.0.0.dist-info/WHEEL
django_webmention-3.0.0.dist-info/top_level.txt
django_webmention-3.0.0.dist-info/RECORD
